cparse/__init__.py
cparse/__main__.py
cparse/css.py
cparse/fpath.py
cparse/htmlparse.py
cparse/js.py
cparse/pyparse.py
cparse/tree.py
cparse/util.py
cparse/css/__init__.py
cparse/css/property.py
cparse/css/rule.py
cparse/css/selector.py
cparse/svg/__init__.py
cparse/svg/parse.py
cparse/svg/path.py
cparse-0.0.2.dist-info/LICENSE
cparse-0.0.2.dist-info/METADATA
cparse-0.0.2.dist-info/WHEEL
cparse-0.0.2.dist-info/entry_points.txt
cparse-0.0.2.dist-info/top_level.txt
cparse-0.0.2.dist-info/RECORD
