Metadata-Version: 2.1
Name: cparse
Version: 0.0.2
Summary: Code parser tool
Home-page: https://github.com/luciancooper/cparse
Author: Lucian Cooper
Author-email: cooperlucian@gmail.com
License: MIT
Project-URL: Documentation, https://cparse.readthedocs.io
Keywords: parser
Platform: UNKNOWN
Classifier: Intended Audience :: Developers
Classifier: License :: OSI Approved :: MIT License
Classifier: Programming Language :: Python
Classifier: Programming Language :: Python :: 3.6
Classifier: Operating System :: MacOS
Classifier: Topic :: Software Development
Classifier: Topic :: Utilities
Requires-Dist: pydecorator
